{
  "db_name": "PostgreSQL",
  "query": "INSERT INTO oauth_authorization_codes\n                             (application_id, account_id, code, redirect_uri, scopes, expires_at)\n                           VALUES ($1, $2, $3, $4, $5, $6)",
  "describe": {
    "columns": [],
    "parameters": {
      "Left": [
        "Uuid",
        "Uuid",
        "Text",
        "Text",
        "Text",
        "Timestamptz"
      ]
    },
    "nullable": []
  },
  "hash": "f2d024105427038415c2add5d7c9c18d199ee6d9c1854816bd180eff85c3af5f"
}
